{
    "gameId": "2fa345ce-4875-4f4f-8618-18fa3879fc95",
    "teams": [
        {
            "id": "7c280ede-9bf1-43f9-a34e-ccd167ecb52e",
            "name": "blue",
            "health": 0,
            "players": [
                {
                    "playerId": "64c1227783316aac13cc9d7c",
                    "guesses": [
                        {
                            "roundNumber": 1,
                            "lat": 64.85250435738278,
                            "lng": -19.97550689033803,
                            "distance": 171653.3843989194,
                            "created": 1734235060306,
                            "isTeamsBestGuessOnRound": true,
                            "score": 4539
                        },
                        {
                            "roundNumber": 2,
                            "lat": 51.825799709406674,
                            "lng": 5.478876499636587,
                            "distance": 155455.9972778576,
                            "created": 1734235092189,
                            "isTeamsBestGuessOnRound": true,
                            "score": 4580
                        },
                        {
                            "roundNumber": 3,
                            "lat": -2.0330586133151565,
                            "lng": 115.95606606087826,
                            "distance": 784483.979018695,
                            "created": 1734235153854,
                            "isTeamsBestGuessOnRound": true,
                            "score": 3213
                        },
                        {
                            "roundNumber": 4,
                            "lat": 37.404694432323765,
                            "lng": 23.204331613337725,
                            "distance": 387241.0091764628,
                            "created": 1734235206973,
                            "isTeamsBestGuessOnRound": true,
                            "score": 4019
                        },
                        {
                            "roundNumber": 5,
                            "lat": 9.069339661090863,
                            "lng": 7.20656113535231,
                            "distance": 80889.5453784084,
                            "created": 1734235273974,
                            "isTeamsBestGuessOnRound": true,
                            "score": 4777
                        },
                        {
                            "roundNumber": 6,
                            "lat": -28.012535978911057,
                            "lng": 153.397929310166,
                            "distance": 2395.3982494221,
                            "created": 1734235305159,
                            "isTeamsBestGuessOnRound": true,
                            "score": 4993
                        },
                        {
                            "roundNumber": 7,
                            "lat": 56.230358113718445,
                            "lng": 13.621069929097297,
                            "distance": 526625.9818353454,
                            "created": 1734235373353,
                            "isTeamsBestGuessOnRound": true,
                            "score": 3716
                        },
                        {
                            "roundNumber": 8,
                            "lat": 50.67377328352305,
                            "lng": 3.4868405718815954,
                            "distance": 599336.6055888868,
                            "created": 1734235427377,
                            "isTeamsBestGuessOnRound": true,
                            "score": 3567
                        }
                    ],
                    "rank": 0,
                    "rating": 966,
                    "countryCode": "jp",
                    "progressChange": {
                        "xpProgressions": [
                            {
                                "xp": 168022,
                                "currentLevel": {
                                    "level": 71,
                                    "xpStart": 167090
                                },
                                "nextLevel": {
                                    "level": 72,
                                    "xpStart": 173450
                                },
                                "currentTitle": {
                                    "id": 220,
                                    "tierId": 80
                                }
                            },
                            {
                                "xp": 168087,
                                "currentLevel": {
                                    "level": 71,
                                    "xpStart": 167090
                                },
                                "nextLevel": {
                                    "level": 72,
                                    "xpStart": 173450
                                },
                                "currentTitle": {
                                    "id": 220,
                                    "tierId": 80
                                }
                            }
                        ],
                        "awardedXp": {
                            "totalAwardedXp": 65,
                            "xpAwards": [
                                {
                                    "xp": 40,
                                    "reason": "DuelCompleted",
                                    "count": 1
                                },
                                {
                                    "xp": 25,
                                    "reason": "Marathon",
                                    "count": 1
                                }
                            ]
                        },
                        "medal": "None",
                        "competitiveProgress": null,
                        "rankedSystemProgress": {
                            "points": {},
                            "totalWeeklyPoints": 0,
                            "weeklyCap": 0,
                            "gamesPlayedWithinWeeklyCap": 0,
                            "positionBefore": 13,
                            "positionAfter": 19,
                            "ratingBefore": 950,
                            "ratingAfter": 932,
                            "winStreak": 0,
                            "bucketSortedBy": "Rating",
                            "gameMode": "NoMoveDuels",
                            "gameModeRatingBefore": 931,
                            "gameModeRatingAfter": 914,
                            "gameModeGamesPlayed": 98,
                            "gameModeGamesRequired": 10,
                            "placementGamesPlayed": 0,
                            "placementGamesRequired": 0
                        },
                        "rankedTeamDuelsProgress": null
                    },
                    "pin": {
                        "lat": 37.826655,
                        "lng": -122.42289
                    },
                    "helpRequested": false,
                    "nick": "masuharu",
                    "avatarPath": "pin/afdcebda024b26a167868e00fcbcb89a.png",
                    "avatar": {
                        "fullBodyPath": "pin/aa7b736d116ce58e448dbeadbd6a36fc.png"
                    },
                    "flair": 0,
                    "isGuest": false,
                    "tierId": 80,
                    "teamName": "blue",
                    "competitive": {
                        "rating": 966,
                        "division": {
                            "type": 40,
                            "startRating": 850,
                            "endRating": 1100
                        }
                    }
                }
            ],
            "roundResults": [
                {
                    "roundNumber": 1,
                    "score": 4539,
                    "healthBefore": 6000,
                    "healthAfter": 5758,
                    "bestGuess": {
                        "roundNumber": 1,
                        "lat": 64.85250435738278,
                        "lng": -19.97550689033803,
                        "distance": 171653.3843989194,
                        "created": "2024-12-15T03:57:40.306+00:00",
                        "isTeamsBestGuessOnRound": true,
                        "score": 4539
                    }
                },
                {
                    "roundNumber": 2,
                    "score": 4580,
                    "healthBefore": 5758,
                    "healthAfter": 5699,
                    "bestGuess": {
                        "roundNumber": 2,
                        "lat": 51.825799709406674,
                        "lng": 5.478876499636587,
                        "distance": 155455.9972778576,
                        "created": "2024-12-15T03:58:12.189+00:00",
                        "isTeamsBestGuessOnRound": true,
                        "score": 4580
                    }
                },
                {
                    "roundNumber": 3,
                    "score": 3213,
                    "healthBefore": 5699,
                    "healthAfter": 4217,
                    "bestGuess": {
                        "roundNumber": 3,
                        "lat": -2.0330586133151565,
                        "lng": 115.95606606087826,
                        "distance": 784483.979018695,
                        "created": "2024-12-15T03:59:13.854+00:00",
                        "isTeamsBestGuessOnRound": true,
                        "score": 3213
                    }
                },
                {
                    "roundNumber": 4,
                    "score": 4019,
                    "healthBefore": 4217,
                    "healthAfter": 3842,
                    "bestGuess": {
                        "roundNumber": 4,
                        "lat": 37.404694432323765,
                        "lng": 23.204331613337725,
                        "distance": 387241.0091764628,
                        "created": "2024-12-15T04:00:06.973+00:00",
                        "isTeamsBestGuessOnRound": true,
                        "score": 4019
                    }
                },
                {
                    "roundNumber": 5,
                    "score": 4777,
                    "healthBefore": 3842,
                    "healthAfter": 3842,
                    "bestGuess": {
                        "roundNumber": 5,
                        "lat": 9.069339661090863,
                        "lng": 7.20656113535231,
                        "distance": 80889.5453784084,
                        "created": "2024-12-15T04:01:13.974+00:00",
                        "isTeamsBestGuessOnRound": true,
                        "score": 4777
                    }
                },
                {
                    "roundNumber": 6,
                    "score": 4993,
                    "healthBefore": 3842,
                    "healthAfter": 3842,
                    "bestGuess": {
                        "roundNumber": 6,
                        "lat": -28.012535978911057,
                        "lng": 153.397929310166,
                        "distance": 2395.3982494221,
                        "created": "2024-12-15T04:01:45.159+00:00",
                        "isTeamsBestGuessOnRound": true,
                        "score": 4993
                    }
                },
                {
                    "roundNumber": 7,
                    "score": 3716,
                    "healthBefore": 3842,
                    "healthAfter": 2032,
                    "bestGuess": {
                        "roundNumber": 7,
                        "lat": 56.230358113718445,
                        "lng": 13.621069929097297,
                        "distance": 526625.9818353454,
                        "created": "2024-12-15T04:02:53.353+00:00",
                        "isTeamsBestGuessOnRound": true,
                        "score": 3716
                    }
                },
                {
                    "roundNumber": 8,
                    "score": 3567,
                    "healthBefore": 2032,
                    "healthAfter": 0,
                    "bestGuess": {
                        "roundNumber": 8,
                        "lat": 50.67377328352305,
                        "lng": 3.4868405718815954,
                        "distance": 599336.6055888868,
                        "created": "2024-12-15T04:03:47.377+00:00",
                        "isTeamsBestGuessOnRound": true,
                        "score": 3567
                    }
                }
            ],
            "isEveryTeamSolo": true
        },
        {
            "id": "a181e8ac-249c-4646-8640-8b5609f7a51f",
            "name": "red",
            "health": 4520,
            "players": [
                {
                    "playerId": "669a021dde26a8b12d76b37d",
                    "guesses": [
                        {
                            "roundNumber": 1,
                            "lat": 64.47363405586732,
                            "lng": -21.939294379745522,
                            "distance": 79533.3090247586,
                            "created": 1734235044124,
                            "isTeamsBestGuessOnRound": true,
                            "score": 4781
                        },
                        {
                            "roundNumber": 2,
                            "lat": 52.1249295549247,
                            "lng": 4.853242282581416,
                            "distance": 132862.3156068658,
                            "created": 1734235090694,
                            "isTeamsBestGuessOnRound": true,
                            "score": 4639
                        },
                        {
                            "roundNumber": 3,
                            "lat": 0.5709116172154053,
                            "lng": 109.84214247351191,
                            "distance": 111594.957912832,
                            "created": 1734235160934,
                            "isTeamsBestGuessOnRound": true,
                            "score": 4695
                        },
                        {
                            "roundNumber": 4,
                            "lat": 38.68097535813956,
                            "lng": 22.17599718640608,
                            "distance": 229076.6042886785,
                            "created": 1734235219497,
                            "isTeamsBestGuessOnRound": true,
                            "score": 4394
                        },
                        {
                            "roundNumber": 5,
                            "lat": 6.766496881257034,
                            "lng": 3.7987799598418537,
                            "distance": 390528.163418605,
                            "created": 1734235266543,
                            "isTeamsBestGuessOnRound": true,
                            "score": 4012
                        },
                        {
                            "roundNumber": 6,
                            "lat": -27.501044052073937,
                            "lng": 153.17540155656673,
                            "distance": 62351.0335633374,
                            "created": 1734235309315,
                            "isTeamsBestGuessOnRound": true,
                            "score": 4827
                        },
                        {
                            "roundNumber": 7,
                            "lat": 59.7077152882234,
                            "lng": 17.980107228021787,
                            "distance": 210748.7056891617,
                            "created": 1734235357340,
                            "isTeamsBestGuessOnRound": true,
                            "score": 4440
                        },
                        {
                            "roundNumber": 8,
                            "lat": 51.38985913146638,
                            "lng": -2.0591947620911544,
                            "distance": 203524.9210427032,
                            "created": 1734235411328,
                            "isTeamsBestGuessOnRound": true,
                            "score": 4458
                        }
                    ],
                    "rank": 0,
                    "rating": 0,
                    "countryCode": "us",
                    "progressChange": {
                        "xpProgressions": [
                            {
                                "xp": 40087,
                                "currentLevel": {
                                    "level": 41,
                                    "xpStart": 40070
                                },
                                "nextLevel": {
                                    "level": 42,
                                    "xpStart": 42590
                                },
                                "currentTitle": {
                                    "id": 130,
                                    "tierId": 50
                                }
                            },
                            {
                                "xp": 40175,
                                "currentLevel": {
                                    "level": 41,
                                    "xpStart": 40070
                                },
                                "nextLevel": {
                                    "level": 42,
                                    "xpStart": 42590
                                },
                                "currentTitle": {
                                    "id": 130,
                                    "tierId": 50
                                }
                            }
                        ],
                        "awardedXp": {
                            "totalAwardedXp": 88,
                            "xpAwards": [
                                {
                                    "xp": 40,
                                    "reason": "DuelCompleted",
                                    "count": 1
                                },
                                {
                                    "xp": 23,
                                    "reason": "HpBonus",
                                    "count": 4520
                                },
                                {
                                    "xp": 25,
                                    "reason": "Marathon",
                                    "count": 1
                                }
                            ]
                        },
                        "medal": "None",
                        "competitiveProgress": null,
                        "rankedSystemProgress": {
                            "points": {},
                            "totalWeeklyPoints": 1811,
                            "weeklyCap": 20,
                            "gamesPlayedWithinWeeklyCap": 20,
                            "positionBefore": 1,
                            "positionAfter": 1,
                            "ratingBefore": 907,
                            "ratingAfter": 925,
                            "winStreak": 4,
                            "bucketSortedBy": "Points",
                            "gameMode": "NoMoveDuels",
                            "gameModeRatingBefore": 913,
                            "gameModeRatingAfter": 930,
                            "gameModeGamesPlayed": 10,
                            "gameModeGamesRequired": 10,
                            "placementGamesPlayed": 0,
                            "placementGamesRequired": 0
                        },
                        "rankedTeamDuelsProgress": null
                    },
                    "pin": null,
                    "helpRequested": false,
                    "nick": "stiles",
                    "avatarPath": "pin/9930a8679e9c28eb8ecef1aa38e3cd09.png",
                    "avatar": {
                        "fullBodyPath": "pin/002212da243913ba996ba946250f6f11.png"
                    },
                    "flair": 0,
                    "isGuest": false,
                    "tierId": 50,
                    "teamName": "red",
                    "competitive": {
                        "rating": 0,
                        "division": {
                            "type": 10,
                            "startRating": 0,
                            "endRating": 450
                        }
                    }
                }
            ],
            "roundResults": [
                {
                    "roundNumber": 1,
                    "score": 4781,
                    "healthBefore": 6000,
                    "healthAfter": 6000,
                    "bestGuess": {
                        "roundNumber": 1,
                        "lat": 64.47363405586732,
                        "lng": -21.939294379745522,
                        "distance": 79533.3090247586,
                        "created": "2024-12-15T03:57:24.124+00:00",
                        "isTeamsBestGuessOnRound": true,
                        "score": 4781
                    }
                },
                {
                    "roundNumber": 2,
                    "score": 4639,
                    "healthBefore": 6000,
                    "healthAfter": 6000,
                    "bestGuess": {
                        "roundNumber": 2,
                        "lat": 52.1249295549247,
                        "lng": 4.853242282581416,
                        "distance": 132862.3156068658,
                        "created": "2024-12-15T03:58:10.694+00:00",
                        "isTeamsBestGuessOnRound": true,
                        "score": 4639
                    }
                },
                {
                    "roundNumber": 3,
                    "score": 4695,
                    "healthBefore": 6000,
                    "healthAfter": 6000,
                    "bestGuess": {
                        "roundNumber": 3,
                        "lat": 0.5709116172154053,
                        "lng": 109.84214247351191,
                        "distance": 111594.957912832,
                        "created": "2024-12-15T03:59:20.934+00:00",
                        "isTeamsBestGuessOnRound": true,
                        "score": 4695
                    }
                },
                {
                    "roundNumber": 4,
                    "score": 4394,
                    "healthBefore": 6000,
                    "healthAfter": 6000,
                    "bestGuess": {
                        "roundNumber": 4,
                        "lat": 38.68097535813956,
                        "lng": 22.17599718640608,
                        "distance": 229076.6042886785,
                        "created": "2024-12-15T04:00:19.497+00:00",
                        "isTeamsBestGuessOnRound": true,
                        "score": 4394
                    }
                },
                {
                    "roundNumber": 5,
                    "score": 4012,
                    "healthBefore": 6000,
                    "healthAfter": 4852,
                    "bestGuess": {
                        "roundNumber": 5,
                        "lat": 6.766496881257034,
                        "lng": 3.7987799598418537,
                        "distance": 390528.163418605,
                        "created": "2024-12-15T04:01:06.543+00:00",
                        "isTeamsBestGuessOnRound": true,
                        "score": 4012
                    }
                },
                {
                    "roundNumber": 6,
                    "score": 4827,
                    "healthBefore": 4852,
                    "healthAfter": 4520,
                    "bestGuess": {
                        "roundNumber": 6,
                        "lat": -27.501044052073937,
                        "lng": 153.17540155656673,
                        "distance": 62351.0335633374,
                        "created": "2024-12-15T04:01:49.315+00:00",
                        "isTeamsBestGuessOnRound": true,
                        "score": 4827
                    }
                },
                {
                    "roundNumber": 7,
                    "score": 4440,
                    "healthBefore": 4520,
                    "healthAfter": 4520,
                    "bestGuess": {
                        "roundNumber": 7,
                        "lat": 59.7077152882234,
                        "lng": 17.980107228021787,
                        "distance": 210748.7056891617,
                        "created": "2024-12-15T04:02:37.34+00:00",
                        "isTeamsBestGuessOnRound": true,
                        "score": 4440
                    }
                },
                {
                    "roundNumber": 8,
                    "score": 4458,
                    "healthBefore": 4520,
                    "healthAfter": 4520,
                    "bestGuess": {
                        "roundNumber": 8,
                        "lat": 51.38985913146638,
                        "lng": -2.0591947620911544,
                        "distance": 203524.9210427032,
                        "created": "2024-12-15T04:03:31.328+00:00",
                        "isTeamsBestGuessOnRound": true,
                        "score": 4458
                    }
                }
            ],
            "isEveryTeamSolo": true
        }
    ],
    "rounds": [
        {
            "roundNumber": 1,
            "panorama": {
                "panoId": "5051346868687A774F3034544B4A3472794554327067",
                "lat": 63.827105497141005,
                "lng": -22.64102437464767,
                "countryCode": "is",
                "heading": 277.8052507968001,
                "pitch": -3.6539581124355607,
                "zoom": 0
            },
            "hasProcessedRoundTimeout": true,
            "isHealingRound": false,
            "multiplier": 1,
            "damageMultiplier": 1,
            "startTime": 1734235027257,
            "endTime": 1734235059124,
            "timerStartTime": 1734235044124
        },
        {
            "roundNumber": 2,
            "panorama": {
                "panoId": "4F595372304C304A6A327366466C683433706B624641",
                "lat": 53.22040260570503,
                "lng": 5.640142456968051,
                "countryCode": "nl",
                "heading": 103.09999454075498,
                "pitch": 11.165273080759944,
                "zoom": 0
            },
            "hasProcessedRoundTimeout": true,
            "isHealingRound": false,
            "multiplier": 1,
            "damageMultiplier": 1,
            "startTime": 1734235073541,
            "endTime": 1734235105694,
            "timerStartTime": 1734235090694
        },
        {
            "roundNumber": 3,
            "panorama": {
                "panoId": "5758573733563843477A643961435A746F61654F6677",
                "lat": 1.5733010715083,
                "lng": 109.8913803684245,
                "countryCode": "my",
                "heading": 22.56077208033305,
                "pitch": -0.038488341044285335,
                "zoom": 0
            },
            "hasProcessedRoundTimeout": true,
            "isHealingRound": false,
            "multiplier": 1,
            "damageMultiplier": 1,
            "startTime": 1734235105305,
            "endTime": 1734235168854,
            "timerStartTime": 1734235153854
        },
        {
            "roundNumber": 4,
            "panorama": {
                "panoId": "565A73545973424D7157376371744C6C4C7648664341",
                "lat": 39.72985443815138,
                "lng": 19.88758323232663,
                "countryCode": "gr",
                "heading": 183.40466222042136,
                "pitch": 3.730510412208872,
                "zoom": 0
            },
            "hasProcessedRoundTimeout": true,
            "isHealingRound": false,
            "multiplier": 1,
            "damageMultiplier": 1,
            "startTime": 1734235173985,
            "endTime": 1734235221973,
            "timerStartTime": 1734235206973
        },
        {
            "roundNumber": 5,
            "panorama": {
                "panoId": "44622D6E50757066372D322D79766677747659707041",
                "lat": 8.391264051938464,
                "lng": 6.940018438730676,
                "countryCode": "ng",
                "heading": 24.63957196225522,
                "pitch": 2.857648083449874,
                "zoom": 0
            },
            "hasProcessedRoundTimeout": true,
            "isHealingRound": false,
            "multiplier": 1.5,
            "damageMultiplier": 1.5,
            "startTime": 1734235232513,
            "endTime": 1734235281543,
            "timerStartTime": 1734235266543
        },
        {
            "roundNumber": 6,
            "panorama": {
                "panoId": "6A583374734669317331583473446C4C594132366A51",
                "lat": -28.01772195025252,
                "lng": 153.42161331523243,
                "countryCode": "au",
                "heading": 86.16008539061804,
                "pitch": 0.34373004962105824,
                "zoom": 0
            },
            "hasProcessedRoundTimeout": true,
            "isHealingRound": false,
            "multiplier": 2,
            "damageMultiplier": 2,
            "startTime": 1734235287193,
            "endTime": 1734235320159,
            "timerStartTime": 1734235305159
        },
        {
            "roundNumber": 7,
            "panorama": {
                "panoId": "774D6F2D6133755839417376434B4D6C783143427941",
                "lat": 60.91007457653664,
                "lng": 15.021434599317288,
                "countryCode": "se",
                "heading": 52.88253609572544,
                "pitch": -1.198801710634697,
                "zoom": 0
            },
            "hasProcessedRoundTimeout": true,
            "isHealingRound": false,
            "multiplier": 2.5,
            "damageMultiplier": 2.5,
            "startTime": 1734235322438,
            "endTime": 1734235372340,
            "timerStartTime": 1734235357340
        },
        {
            "roundNumber": 8,
            "panorama": {
                "panoId": "6B355236794F495230347A38325F684D544B72656241",
                "lat": 51.63941758263631,
                "lng": -4.973120489726382,
                "countryCode": "gb",
                "heading": 103.05513694317752,
                "pitch": -3.1512711213278095,
                "zoom": 0
            },
            "hasProcessedRoundTimeout": true,
            "isHealingRound": false,
            "multiplier": 3,
            "damageMultiplier": 3,
            "startTime": 1734235386445,
            "endTime": 1734235426328,
            "timerStartTime": 1734235411328
        }
    ],
    "currentRoundNumber": 8,
    "status": "Finished",
    "version": 72,
    "options": {
        "initialHealth": 6000,
        "roundTime": 15,
        "maxRoundTime": 0,
        "gracePeriodTime": 1,
        "gameTimeOut": 7200,
        "maxNumberOfRounds": 0,
        "healingRounds": [
            5
        ],
        "movementOptions": {
            "forbidMoving": true,
            "forbidZooming": false,
            "forbidRotating": false
        },
        "mapSlug": "652ba0d9002aa0d36f996153",
        "isRated": true,
        "map": {
            "name": "An Official World",
            "slug": "652ba0d9002aa0d36f996153",
            "bounds": {
                "min": {
                    "lat": -77.84586512929343,
                    "lng": -177.3841988830772
                },
                "max": {
                    "lat": 81.68122210663999,
                    "lng": 178.8066336283942
                }
            },
            "maxErrorDistance": 17739828
        },
        "duelRoundOptions": [],
        "roundsWithoutDamageMultiplier": 4,
        "disableMultipliers": false,
        "multiplierIncrement": 5,
        "disableHealing": true,
        "isTeamDuels": false,
        "gameContext": {
            "type": "None",
            "id": ""
        },
        "roundStartingBehavior": "Default",
        "flashbackRounds": [],
        "competitiveGameMode": "NoMoveDuels",
        "countAllGuesses": false,
        "masterControlAutoStartRounds": false,
        "consumedLocationsIdentifier": "",
        "useCuratedLocations": false,
        "extraWaitTimeBetweenRounds": 0
    },
    "movementOptions": {
        "forbidMoving": true,
        "forbidZooming": false,
        "forbidRotating": false
    },
    "mapBounds": {
        "min": {
            "lat": -77.84586512929343,
            "lng": -177.3841988830772
        },
        "max": {
            "lat": 81.68122210663999,
            "lng": 178.8066336283942
        }
    },
    "initialHealth": 6000,
    "maxNumberOfRounds": 0,
    "result": {
        "isDraw": false,
        "winningTeamId": "a181e8ac-249c-4646-8640-8b5609f7a51f",
        "winnerStyle": "Victory"
    },
    "isPaused": false,
    "gameType": "Duels",
    "partyId": null,
    "isRated": true,
    "tournament": null
}